nonebot/adapters/red/__init__.py
nonebot/adapters/red/adapter.py
nonebot/adapters/red/api/__init__.py
nonebot/adapters/red/api/handle.py
nonebot/adapters/red/api/model.py
nonebot/adapters/red/bot.py
nonebot/adapters/red/compat.py
nonebot/adapters/red/config.py
nonebot/adapters/red/event.py
nonebot/adapters/red/message.py
nonebot/adapters/red/permission.py
nonebot/adapters/red/utils.py
nonebot_adapter_red-0.9.0.dist-info/METADATA
nonebot_adapter_red-0.9.0.dist-info/WHEEL
nonebot_adapter_red-0.9.0.dist-info/licenses/LICENSE
nonebot_adapter_red-0.9.0.dist-info/RECORD
