Metadata-Version: 2.1
Name: nonebot-adapter-red
Version: 0.9.0
Summary: Red Protocol Adapter for Nonebot2
Home-page: https://github.com/nonebot/adapter-red
Author: zhaomaoniu
Author-Email: RF-Tar-Railt <rf_tar_railt@qq.com>
License: MIT
Project-URL: Homepage, https://github.com/nonebot/adapter-red
Project-URL: Repository, https://github.com/nonebot/adapter-red
Requires-Python: >=3.8
Requires-Dist: nonebot2>=2.2.0
Requires-Dist: packaging>=23.1
Requires-Dist: PyYAML; extra == "auto-detect"
Provides-Extra: auto_detect
